sayhours/__init__.py
sayhours/__main__.py
sayhours/sounds/00/00-estel-1.ogg
sayhours/sounds/00/00-estel-2.ogg
sayhours/sounds/00/00-estel-3.ogg
sayhours/sounds/00/00-estel-4.ogg
sayhours/sounds/00/00-estel-5.ogg
sayhours/sounds/00/00-hex-1.ogg
sayhours/sounds/00/00-hex-2.ogg
sayhours/sounds/00/00-hex-3.ogg
sayhours/sounds/00/00-hex-4.ogg
sayhours/sounds/01/01-estel-2.ogg
sayhours/sounds/01/01-estel.ogg
sayhours/sounds/01/01-hex.ogg
sayhours/sounds/02/02-estel-2.ogg
sayhours/sounds/02/02-estel-3.ogg
sayhours/sounds/02/02-estel-4.ogg
sayhours/sounds/02/02-estel.ogg
sayhours/sounds/02/02-hex-2.ogg
sayhours/sounds/02/02-hex.ogg
sayhours/sounds/03/03-estel.ogg
sayhours/sounds/03/03-hex.ogg
sayhours/sounds/04/04-estel-2.ogg
sayhours/sounds/04/04-estel.ogg
sayhours/sounds/04/04-hex.ogg
sayhours/sounds/05/05-estel-2.ogg
sayhours/sounds/05/05-estel-3.ogg
sayhours/sounds/05/05-estel-4.ogg
sayhours/sounds/05/05-estel.ogg
sayhours/sounds/05/05-hex-2.ogg
sayhours/sounds/05/05-hex.ogg
sayhours/sounds/06/06-estel.ogg
sayhours/sounds/06/06-hex.ogg
sayhours/sounds/07/07-estel.ogg
sayhours/sounds/07/07-hex-2.ogg
sayhours/sounds/07/07-hex.ogg
sayhours/sounds/08/08-estel.ogg
sayhours/sounds/08/08-hex.ogg
sayhours/sounds/09/09-estel.ogg
sayhours/sounds/09/09-hex.ogg
sayhours/sounds/10/10-estel-2.ogg
sayhours/sounds/10/10-estel.ogg
sayhours/sounds/10/10-hex-2.ogg
sayhours/sounds/10/10-hex.ogg
sayhours/sounds/11/11-estel.ogg
sayhours/sounds/11/11-hex.ogg
sayhours/sounds/12/12-estel-2.ogg
sayhours/sounds/12/12-estel-3.ogg
sayhours/sounds/12/12-estel-4.ogg
sayhours/sounds/12/12-estel-5.ogg
sayhours/sounds/12/12-estel-6.ogg
sayhours/sounds/12/12-estel.ogg
sayhours/sounds/12/12-hex-2.ogg
sayhours/sounds/12/12-hex-3.ogg
sayhours/sounds/12/12-hex-4.ogg
sayhours/sounds/12/12-hex.ogg
sayhours/sounds/13/13-estel-2.ogg
sayhours/sounds/13/13-estel-3.ogg
sayhours/sounds/13/13-estel.ogg
sayhours/sounds/13/13-hex-2.ogg
sayhours-1.0.dist-info/DESCRIPTION.rst
sayhours-1.0.dist-info/METADATA
sayhours-1.0.dist-info/RECORD
sayhours-1.0.dist-info/WHEEL
sayhours-1.0.dist-info/metadata.json
sayhours-1.0.dist-info/top_level.txt
