Metadata-Version: 2.0
Name: sayhours
Version: 1.0
Summary: Speaks current time aloud.
Home-page: https://umonkey.net/
Author: Justin Forest
Author-email: hex@umonkey.net
License: GNU GPL
Platform: UNKNOWN
Classifier: License :: OSI Approved :: GNU General Public License (GPL)
Classifier: Natural Language :: English
Classifier: Operating System :: Unix
Classifier: Programming Language :: Python
